LICENSE.txt
MANIFEST.in
README.rst
pyproject.toml
setup.py
tutor_notes.egg-info/PKG-INFO
tutor_notes.egg-info/SOURCES.txt
tutor_notes.egg-info/dependency_links.txt
tutor_notes.egg-info/entry_points.txt
tutor_notes.egg-info/requires.txt
tutor_notes.egg-info/top_level.txt
tutornotes/__about__.py
tutornotes/__init__.py
tutornotes/plugin.py
tutornotes/patches/caddyfile
tutornotes/patches/k8s-deployments
tutornotes/patches/k8s-jobs
tutornotes/patches/k8s-services
tutornotes/patches/kustomization-configmapgenerator
tutornotes/patches/local-docker-compose-dev-services
tutornotes/patches/local-docker-compose-jobs-services
tutornotes/patches/local-docker-compose-permissions-command
tutornotes/patches/local-docker-compose-permissions-volumes
tutornotes/patches/local-docker-compose-services
tutornotes/patches/openedx-common-settings
tutornotes/patches/openedx-lms-common-settings
tutornotes/patches/openedx-lms-development-settings
tutornotes/patches/openedx-lms-production-settings
tutornotes/templates/notes/apps/settings/tutor.py
tutornotes/templates/notes/build/notes/Dockerfile
tutornotes/templates/notes/tasks/lms/init
tutornotes/templates/notes/tasks/mysql/init
tutornotes/templates/notes/tasks/notes/init